{
  "S_Crush": {
    "name": "Crush",
    "className": "game.skills.trees.equipment.hammer.S_Crush",
    "description": "Give Immobile 1.",
    "iconPath": "icons/skills/wingedboots.png",
    "targetType": "SINGLE",
    "damageMode": "PHYSICAL",
    "damageType": "NORMAL",
    "tags": [
      "PRIMARY",
      "WEAPON"
    ],
    "accuracy": 85,
    "dmgMultipliers": [
      {
        "prof": "BODY",
        "percentage": 0.2
      }
    ],
    "effects": [
      {
        "className": "game.effects.status.Immobile",
        "turns": 1
      }
    ],
    "possibleCastPositions": [
      3
    ],
    "possibleTargetPositions": [
      4
    ]
  },
  "S_Merciless": {
    "name": "Merciless",
    "className": "game.skills.trees.equipment.hammer.S_Merciless",
    "description": "Give Dazed 1.",
    "iconPath": "icons/skills/wingedboots.png",
    "targetType": "SINGLE",
    "damageMode": "PHYSICAL",
    "damageType": "NORMAL",
    "tags": [
      "PRIMARY",
      "WEAPON"
    ],
    "accuracy": 90,
    "dmgMultipliers": [
      {
        "prof": "BODY",
        "percentage": 0.15
      }
    ],
    "effects": [
      {
        "className": "game.effects.status.Dazed",
        "turns": 1
      }
    ],
    "possibleCastPositions": [
      3
    ],
    "possibleTargetPositions": [
      4
    ]
  },
  "S_Brainsplitter": {
    "name": "Brainsplitter",
    "className": "game.skills.trees.equipment.hammer.S_Brainsplitter",
    "description": "If the target has a Status, give Brittle 1. Heal for 50% of the damage dealt.",
    "iconPath": "icons/skills/wingedboots.png",
    "targetType": "ALL_TARGETS",
    "damageMode": "PHYSICAL",
    "damageType": "NORMAL",
    "tags": [
      "TACTICAL",
      "WEAPON"
    ],
    "maxCd": 3,
    "dmgMultipliers": [
      {
        "prof": "BODY",
        "percentage": 0.35
      }
    ],
    "effects": [
      {
        "className": "game.effects.stat.Brittle",
        "stacks": 0,
        "turns": 1,
        "condition": {
          "trigger": "TARGET",
          "hasStatus": true
        }
      }
    ],
    "subscriptions": [
      {
        "topicName": "DMG_TRIGGER",
        "methodName": "dmgTrigger",
        "trigger": {
          "casterHeroReference": "SAME",
          "targetHasStatusDebuff": true
        }
      }
    ],
    "possibleCastPositions": [
      2,
      3
    ],
    "possibleTargetPositions": [
      4,
      5
    ],
    "keyValues": {
      "HealPercentage": 0.5
    }
  },
  "S_FullSwing": {
    "name": "Full Swing",
    "className": "game.skills.trees.equipment.hammer.S_FullSwing",
    "description": "Stun.",
    "iconPath": "icons/skills/wingedboots.png",
    "targetType": "SINGLE",
    "tags": [
      "TACTICAL",
      "WEAPON"
    ],
    "accuracy": 70,
    "damageType": "NORMAL",
    "damageMode": "PHYSICAL",
    "push": 1,
    "maxCd": 4,
    "manaCost": 20,
    "dmgMultipliers": [
      {
        "prof": "BODY",
        "percentage": 0.5
      }
    ],
    "effects": [
      {
        "className": "game.effects.status.Stunned",
        "turns": 1
      }
    ],
    "possibleCastPositions": [
      3
    ],
    "possibleTargetPositions": [
      4,
      5
    ]
  },
  "S_TakeCover": {
    "name": "Take Cover",
    "className": "game.skills.trees.equipment.shield.S_TakeCover",
    "description": "Receive Prepared 1. If you are Mighty, receive Protected.",
    "iconPath": "icons/skills/wingedboots.png",
    "targetType": "SELF",
    "tags": [
      "PRIMARY",
      "WEAPON"
    ],
    "maxCd": 2,
    "effects": [
      {
        "className": "game.effects.hero.Prepared",
        "turns": 1
      },
      {
        "className": "game.effects.status.Protected",
        "condition": {
          "trigger": "CASTER",
          "effectName": "game.effects.stat.Mighty",
          "hasCheck": true
        }
      }
    ],
    "possibleCastPositions": [
      0,
      1,
      2,
      3
    ]
  },
  "S_ShieldBash": {
    "name": "Shield Bash",
    "className": "game.skills.trees.equipment.shield.S_ShieldBash",
    "description": "Push 1. If you are Mighty, stun.",
    "iconPath": "icons/skills/wingedboots.png",
    "targetType": "SINGLE",
    "tags": [
      "TACTICAL",
      "WEAPON"
    ],
    "damageType": "NORMAL",
    "damageMode": "PHYSICAL",
    "maxCd": 3,
    "push": 1,
    "effects": [
      {
        "className": "game.effects.status.Stunned",
        "stacks": 0,
        "turns": 1,
        "condition": {
          "trigger": "CASTER",
          "effectName": "game.effects.stat.Mighty",
          "hasCheck": true
        }
      }
    ],
    "possibleCastPositions": [
      3
    ],
    "possibleTargetPositions": [
      4
    ]
  },
  "S_Dice": {
    "name": "Dice",
    "className": "game.skills.trees.equipment.sword.S_Dice",
    "description": "If you have Advantage, mark the target.",
    "iconPath": "icons/skills/wingedboots.png",
    "targetType": "SINGLE",
    "tags": [
      "PRIMARY",
      "WEAPON"
    ],
    "damageType": "NORMAL",
    "damageMode": "PHYSICAL",
    "dmgMultipliers": [
      {
        "prof": "BODY",
        "percentage": 0.25
      },
      {
        "prof": "DEXTERITY",
        "percentage": 0.35
      }
    ],
    "effects": [
      {
        "className": "game.effects.hero.Marked",
        "condition": {
          "trigger": "CASTER",
          "effectName": "Advantage",
          "hasCheck": true
        }
      }
    ],
    "possibleCastPositions": [
      2,
      3
    ],
    "possibleTargetPositions": [
      4,
      5
    ]
  },
  "S_Slice": {
    "name": "Slice",
    "className": "game.skills.trees.equipment.sword.S_Slice",
    "description": "Receive Advantage.",
    "iconPath": "icons/skills/wingedboots.png",
    "targetType": "SINGLE",
    "tags": [
      "PRIMARY",
      "WEAPON"
    ],
    "damageType": "NORMAL",
    "damageMode": "PHYSICAL",
    "dmgMultipliers": [
      {
        "prof": "BODY",
        "percentage": 0.25
      },
      {
        "prof": "DEXTERITY",
        "percentage": 0.35
      }
    ],
    "casterEffects": [
      {
        "className": "game.effects.hero.Advantage"
      }
    ],
    "possibleCastPositions": [
      2,
      3
    ],
    "possibleTargetPositions": [
      4,
      5
    ]
  },
  "S_DuelingSlash": {
    "name": "Dueling Slash",
    "className": "game.skills.trees.equipment.sword.S_DuelingSlash",
    "description": "If you have Advantage, move forward. Otherwise move back.",
    "iconPath": "icons/skills/wingedboots.png",
    "targetType": "SINGLE",
    "tags": [
      "TACTICAL",
      "WEAPON"
    ],
    "damageType": "NORMAL",
    "damageMode": "PHYSICAL",
    "maxCd": 3,
    "manaCost": 15,
    "dmgMultipliers": [
      {
        "prof": "BODY",
        "percentage": 0.05
      },
      {
        "prof": "DEXTERITY",
        "percentage": 0.45
      }
    ],
    "subscriptions": [
      {
        "topicName": "CAST_CHANGE",
        "methodName": "castChange",
        "trigger": {
          "casterHeroReference": "SAME"
        }
      }
    ],
    "possibleCastPositions": [
      2,
      3
    ],
    "possibleTargetPositions": [
      4,
      5
    ]
  },
  "S_ShatterSwing": {
    "name": "Shatter Swing",
    "className": "game.skills.trees.equipment.sword.S_ShatterSwing",
    "description": "50% Chance to stun. 100% if you have Advantage.",
    "iconPath": "icons/skills/wingedboots.png",
    "targetType": "ALL_TARGETS",
    "tags": [
      "TACTICAL",
      "WEAPON"
    ],
    "damageType": "NORMAL",
    "damageMode": "PHYSICAL",
    "maxCd": 4,
    "manaCost": 20,
    "dmgMultipliers": [
      {
        "prof": "BODY",
        "percentage": 0.4
      },
      {
        "prof": "DEXTERITY",
        "percentage": 0.3
      }
    ],
    "effects": [
      {
        "className": "game.effects.status.Stunned",
        "turns": 1,
        "condition": {
          "successChance": 50
        }
      }
    ],
    "subscriptions": [
      {
        "topicName": "CHANCE_EFFECT_MULT_CHANGE",
        "methodName": "chanceChange",
        "trigger": {
          "casterHeroReference": "SAME",
          "casterEffects": {
            "boolLogic": "ALL_OF",
            "objects": [
              "Advantage"
            ]
          },
          "effects": {
            "boolLogic": "ALL_OF",
            "objects": [
              "Stunned"
            ]
          },
          "skillName": "S_ShatterSwing"
        }
      }
    ],
    "possibleCastPositions": [
      3
    ],
    "possibleTargetPositions": [
      4,
      5
    ]
  },
  "S_DaggerThrow": {
    "name": "Dagger Throw",
    "className": "game.skills.trees.equipment.dagger.S_DaggerThrow",
    "description": " ",
    "iconPath": "icons/skills/wingedboots.png",
    "targetType": "SINGLE",
    "tags": [
      "PRIMARY",
      "WEAPON"
    ],
    "damageType": "NORMAL",
    "damageMode": "PHYSICAL",
    "accuracy": 90,
    "dmgMultipliers": [
      {
        "prof": "DEXTERITY",
        "percentage": 0.55
      }
    ],
    "possibleCastPositions": [
      0,
      1,
      2
    ],
    "possibleTargetPositions": [
      4,
      5,
      6
    ]
  },
  "S_GoForTheThroat": {
    "name": "Go For The Throat",
    "className": "game.skills.trees.equipment.dagger.S_GoForTheThroat",
    "description": "20 Lethality.",
    "iconPath": "icons/skills/wingedboots.png",
    "targetType": "SINGLE",
    "tags": [
      "PRIMARY",
      "WEAPON"
    ],
    "damageType": "NORMAL",
    "damageMode": "PHYSICAL",
    "lethality": 20,
    "dmgMultipliers": [
      {
        "prof": "DEXTERITY",
        "percentage": 0.55
      }
    ],
    "possibleCastPositions": [
      1,
      2,
      3
    ],
    "possibleTargetPositions": [
      4
    ]
  },
  "S_AnkleSlice": {
    "name": "Ankle Slice",
    "className": "game.skills.trees.equipment.dagger.S_AnkleSlice",
    "description": "Give Immobile 1 and Shaken 1. 10 Lethality.",
    "iconPath": "icons/skills/wingedboots.png",
    "targetType": "SINGLE",
    "tags": [
      "TACTICAL",
      "WEAPON"
    ],
    "damageType": "NORMAL",
    "damageMode": "PHYSICAL",
    "accuracy": 95,
    "lethality": 10,
    "maxCd": 3,
    "manaCost": 20,
    "dmgMultipliers": [
      {
        "prof": "DEXTERITY",
        "percentage": 0.55
      }
    ],
    "effects": [
      {
        "className": "game.effects.status.Immobile",
        "turns": 1
      },
      {
        "className": "game.effects.stat.Shaken",
        "turns": 1
      }
    ],
    "possibleCastPositions": [
      1,
      2,
      3
    ],
    "possibleTargetPositions": [
      4,
      5
    ]
  },
  "S_Shiv": {
    "name": "Shiv",
    "className": "game.skills.trees.equipment.dagger.S_Shiv",
    "description": "Hits thrice.",
    "iconPath": "icons/skills/wingedboots.png",
    "targetType": "SINGLE",
    "tags": [
      "TACTICAL",
      "WEAPON"
    ],
    "damageType": "NORMAL",
    "damageMode": "PHYSICAL",
    "maxCd": 5,
    "manaCost": 25,
    "countsAsHits": 3,
    "lethality": 10,
    "dmgMultipliers": [
      {
        "prof": "DEXTERITY",
        "percentage": 0.4
      }
    ],
    "possibleCastPositions": [
      1,
      2,
      3
    ],
    "possibleTargetPositions": [
      4
    ]
  },
  "S_WeightedArrow": {
    "name": "Weighted Arrow",
    "className": "game.skills.trees.equipment.bow.S_WeightedArrow",
    "description": "25% Chance to give Brittle 1.",
    "iconPath": "icons/skills/wingedboots.png",
    "targetType": "SINGLE",
    "tags": [
      "PRIMARY",
      "WEAPON"
    ],
    "damageType": "NORMAL",
    "damageMode": "PHYSICAL",
    "dmgMultipliers": [
      {
        "prof": "DEXTERITY",
        "percentage": 0.3
      }
    ],
    "effects": [
      {
        "className": "game.effects.stat.Brittle",
        "turns": 1,
        "condition": {
          "successChance": 25
        }
      }
    ],
    "possibleCastPositions": [
      0,
      1,
      2,
      3
    ],
    "possibleTargetPositions": [
      4,5
    ]
  },
  "S_AimedShot": {
    "name": "Aimed Shot",
    "className": "game.skills.trees.equipment.bow.S_AimedShot",
    "description": "5 Lethality",
    "iconPath": "icons/skills/wingedboots.png",
    "targetType": "SINGLE",
    "tags": [
      "PRIMARY",
      "WEAPON"
    ],
    "damageType": "NORMAL",
    "damageMode": "PHYSICAL",
    "lethality": 5,
    "dmgMultipliers": [
      {
        "prof": "DEXTERITY",
        "percentage": 0.4
      }
    ],
    "possibleCastPositions": [
      0,
      1
    ],
    "possibleTargetPositions": [
      4,
      5
    ]
  },
  "S_CripplingShot": {
    "name": "Crippling Shot",
    "className": "game.skills.trees.equipment.bow.S_CripplingShot",
    "description": "Give Immobile 3. 75% Body chance to give Bleeding 2.",
    "iconPath": "icons/skills/wingedboots.png",
    "targetType": "ALL_TARGETS",
    "tags": [
      "TACTICAL",
      "WEAPON"
    ],
    "accuracy": 90,
    "maxCd": 3,
    "damageType": "NORMAL",
    "damageMode": "PHYSICAL",
    "manaCost": 20,
    "dmgMultipliers": [
      {
        "prof": "DEXTERITY",
        "percentage": 0.45
      }
    ],
    "effects": [
      {
        "className": "game.effects.status.Bleeding",
        "turns": 2,
        "condition": {
          "successChance": 75,
          "successByCasterStat": "BODY"
        }
      },
      {
        "className": "game.effects.status.Immobile",
        "turns": 3
      }
    ],
    "possibleCastPositions": [
      0,
      1
    ],
    "possibleTargetPositions": [
      4,
      5
    ]
  },
  "S_Barrage": {
    "name": "Barrage",
    "className": "game.skills.trees.equipment.bow.S_Barrage",
    "description": " ",
    "iconPath": "icons/skills/wingedboots.png",
    "targetType": "ALL_TARGETS",
    "tags": [
      "TACTICAL",
      "WEAPON"
    ],
    "accuracy": 85,
    "maxCd": 2,
    "manaCost": 30,
    "countsAsHits": 2,
    "damageType": "NORMAL",
    "damageMode": "PHYSICAL",
    "dmgMultipliers": [
      {
        "prof": "DEXTERITY",
        "percentage": 0.2
      }
    ],
    "possibleCastPositions": [
      0,
      1
    ],
    "possibleTargetPositions": [
      4,
      5,
      6,
      7
    ]
  }
}